alianator/__init__.py
alianator/alianator.py
alianator/diagnostic.py
alianator/templates/diagnostic.yml.jinja
alianator-4.0.2.dist-info/LICENSE.md
alianator-4.0.2.dist-info/WHEEL
alianator-4.0.2.dist-info/METADATA
alianator-4.0.2.dist-info/RECORD
