Metadata-Version: 2.1
Name: alianator
Version: 4.0.2
Summary: A Discord permission name resolver for Pycord
Home-page: https://github.com/celsiusnarhwal/alianator
License: MIT
Keywords: discord,permissions,aliases,pycord
Author: celsius narhwal
Author-email: celsiusnarhwal@gmail.com
Requires-Python: >=3.8,<4.0
Classifier: License :: OSI Approved :: MIT License
Classifier: Programming Language :: Python :: 3
Classifier: Programming Language :: Python :: 3.8
Classifier: Programming Language :: Python :: 3.9
Classifier: Programming Language :: Python :: 3.10
Classifier: Programming Language :: Python :: 3.11
Requires-Dist: jinja2 (>=3.1.2,<4.0.0)
Requires-Dist: multimethod (>=1.9.1,<2.0.0)
Requires-Dist: py-cord (>=1.7.3,<3.0.0)
Requires-Dist: pydantic (>=1.10.4,<2.0.0)
Requires-Dist: titlecase (==2.3)
